perplexity_dev_ti/__init__.py
perplexity_dev_ti/api_client.py
perplexity_dev_ti/api_response.py
perplexity_dev_ti/configuration.py
perplexity_dev_ti/exceptions.py
perplexity_dev_ti/py.typed
perplexity_dev_ti/rest.py
perplexity_dev_ti/api/__init__.py
perplexity_dev_ti/api/default_api.py
perplexity_dev_ti/models/__init__.py
perplexity_dev_ti/models/chat_completion_request.py
perplexity_dev_ti/models/chat_completion_response.py
perplexity_dev_ti/models/choice.py
perplexity_dev_ti/models/choice_delta.py
perplexity_dev_ti/models/message.py
perplexity_dev_ti/models/usage.py
perplexity_dev_ti-0.0.1.dist-info/METADATA
perplexity_dev_ti-0.0.1.dist-info/WHEEL
perplexity_dev_ti-0.0.1.dist-info/top_level.txt
perplexity_dev_ti-0.0.1.dist-info/RECORD
